README.md
setup.py
calculador_de_elementos_estruturais/__init__.py
calculador_de_elementos_estruturais/barra_tracionada.py
calculador_de_elementos_estruturais/calculador_barra_tracionada.py
calculador_de_elementos_estruturais/calculador_cantoneira_tracionada.py
calculador_de_elementos_estruturais/calculador_ligacao.py
calculador_de_elementos_estruturais/calculador_ligacao_dupla.py
calculador_de_elementos_estruturais/calculador_parafusada.py
calculador_de_elementos_estruturais/calculadores.py
calculador_de_elementos_estruturais/cantoneira_tracionada.py
calculador_de_elementos_estruturais/enunciado_ligacao.py
calculador_de_elementos_estruturais/enunciado_ligacao_dupla.py
calculador_de_elementos_estruturais/enunciado_pv.py
calculador_de_elementos_estruturais/informacoes.py
calculador_de_elementos_estruturais/input_normalizado.py
calculador_de_elementos_estruturais/ligacao_corte_duplo.py
calculador_de_elementos_estruturais/ligacao_parafusada.py
calculador_de_elementos_estruturais/menu.py
calculador_de_elementos_estruturais/pegador_ligacao.py
calculador_de_elementos_estruturais/pegador_ligacao_dupla.py
calculador_de_elementos_estruturais/pegador_parafusada.py
calculador_de_elementos_estruturais/pegadores.py
calculador_de_elementos_estruturais/pilar_de_madeira.py
calculador_de_elementos_estruturais/viga_de_madeira.py
calculador_de_elementos_estruturais.egg-info/PKG-INFO
calculador_de_elementos_estruturais.egg-info/SOURCES.txt
calculador_de_elementos_estruturais.egg-info/dependency_links.txt
calculador_de_elementos_estruturais.egg-info/requires.txt
calculador_de_elementos_estruturais.egg-info/top_level.txt