Metadata-Version: 1.0
Name: calculador-de-elementos-estruturais
Version: 0.4.4
Summary: Calculador de Elementos Estruturais
Home-page: UNKNOWN
Author: Doglas Rocha
Author-email: UNKNOWN
License: Boost Software License
Keywords: Vigas,Pilares,Ligação Corte Duplo
Platform: UNKNOWN
